dagster_github/__init__.py
dagster_github/resources.py
dagster_github/version.py
dagster_github-1.0.5.dist-info/LICENSE
dagster_github-1.0.5.dist-info/METADATA
dagster_github-1.0.5.dist-info/WHEEL
dagster_github-1.0.5.dist-info/top_level.txt
dagster_github-1.0.5.dist-info/RECORD
